elasticsearch_shell/__init__.py
elasticsearch_shell/elasticsearch_shell.py
elasticsearch_shell-0.1.0.dist-info/METADATA
elasticsearch_shell-0.1.0.dist-info/WHEEL
elasticsearch_shell-0.1.0.dist-info/entry_points.txt
elasticsearch_shell-0.1.0.dist-info/RECORD
