Metadata-Version: 2.4
Name: elasticsearch-shell
Version: 0.1.0
Summary: A REPL for Elasticsearch.
Author-email: Adrian Lopez <adrianlzt@gmail.com>
Classifier: License :: OSI Approved :: MIT License
Classifier: Operating System :: OS Independent
Classifier: Programming Language :: Python :: 3
Requires-Python: >=3.13
Requires-Dist: elasticsearch==8.17.1
Requires-Dist: prompt-toolkit
